Metadata-Version: 1.0
Name: zjy-demo
Version: 0.1
Summary: This is my demo test
Home-page: UNKNOWN
Author: zjy
Author-email: 331182615@qq.com
License: MIT
Platform: UNKNOWN
